nisanyan_crawler/__init__.py
nisanyan_crawler/__main__.py
nisanyan_crawler/crawler.py
nisanyan_crawler-0.0.2.dist-info/METADATA
nisanyan_crawler-0.0.2.dist-info/WHEEL
nisanyan_crawler-0.0.2.dist-info/entry_points.txt
nisanyan_crawler-0.0.2.dist-info/top_level.txt
nisanyan_crawler-0.0.2.dist-info/RECORD
