Metadata-Version: 2.1
Name: nisanyan-crawler
Version: 0.0.2
Summary: UNKNOWN
Home-page: https://github.com/agmmnn/nisanyan_crawler
Author: agmmnn
License: Apache License Version 2.0
Platform: UNKNOWN
Classifier: Programming Language :: Python :: 3
Classifier: License :: OSI Approved :: Apache Software License
Classifier: Operating System :: OS Independent
Classifier: Environment :: Console
Classifier: Topic :: Utilities
Requires-Python: >=3.5
Requires-Dist: requests
Requires-Dist: beautifulsoup4
Requires-Dist: orjson
